plastron/namespaces/__init__.py
plastron/utils/__init__.py
plastron_utils-4.6.2.dist-info/METADATA
plastron_utils-4.6.2.dist-info/WHEEL
plastron_utils-4.6.2.dist-info/top_level.txt
plastron_utils-4.6.2.dist-info/RECORD
