Metadata-Version: 2.4
Name: plastron-utils
Version: 4.6.2
Summary: Utility functions and namespace definitions for Plastron
Author-email: University of Maryland Libraries <lib-ssdr@umd.edu>, Josh Westgard <westgard@umd.edu>, Peter Eichman <peichman@umd.edu>, Mohamed Abdul Rasheed <mohideen@umd.edu>, Ben Wallberg <wallberg@umd.edu>, David Steelman <dsteelma@umd.edu>, Marc Andreu Grillo Aguilar <aguilarm@umd.edu>
Project-URL: Homepage, https://github.com/umd-lib/plastron
Project-URL: Bug Reports, https://github.com/umd-lib/plastron/issues
Project-URL: Source, https://github.com/umd-lib/plastron
Requires-Python: >=3.10
Requires-Dist: rdflib
Provides-Extra: test
Requires-Dist: pytest; extra == "test"
Requires-Dist: pytest-cov; extra == "test"
